up/__init__.py
up/cli.py
up/commands/__init__.py
up/commands/init.py
up/commands/new.py
up/templates/__init__.py
up/templates/config/__init__.py
up/templates/docs_skill/__init__.py
up/templates/learn/__init__.py
up/templates/loop/__init__.py
up_cli-0.1.1.dist-info/METADATA
up_cli-0.1.1.dist-info/WHEEL
up_cli-0.1.1.dist-info/entry_points.txt
up_cli-0.1.1.dist-info/RECORD
