Metadata-Version: 2.4
Name: up-cli
Version: 0.1.1
Summary: AI-powered project scaffolding with docs, learn, and product-loop systems
Project-URL: Homepage, https://github.com/yourusername/up-cli
Project-URL: Documentation, https://github.com/yourusername/up-cli#readme
Project-URL: Repository, https://github.com/yourusername/up-cli
Author-email: Your Name <you@example.com>
License-Expression: MIT
Keywords: ai,claude,cli,cursor,productivity,scaffolding
Classifier: Development Status :: 3 - Alpha
Classifier: Environment :: Console
Classifier: Intended Audience :: Developers
Classifier: License :: OSI Approved :: MIT License
Classifier: Programming Language :: Python :: 3
Classifier: Programming Language :: Python :: 3.10
Classifier: Programming Language :: Python :: 3.11
Classifier: Programming Language :: Python :: 3.12
Classifier: Topic :: Software Development :: Code Generators
Requires-Python: >=3.10
Requires-Dist: click>=8.0
Requires-Dist: pyyaml>=6.0
Requires-Dist: rich>=13.0
Provides-Extra: dev
Requires-Dist: pytest>=7.0; extra == 'dev'
Requires-Dist: ruff>=0.1.0; extra == 'dev'
